sifu/__init__.py
sifu/api/__init__.py
sifu/app.py
sifu/config.py
sifu/context/__init__.py
sifu/knowledge/__init__.py
sifu/language/__init__.py
sifu/learning/__init__.py
sifu/matcher/__init__.py
sifu-0.1.0.dist-info/LICENSE
sifu-0.1.0.dist-info/METADATA
sifu-0.1.0.dist-info/WHEEL
sifu-0.1.0.dist-info/RECORD
