Metadata-Version: 2.3
Name: sifu
Version: 0.1.0
Summary: Enhanced Knowledge System for ELLMa
License: Apache 2.0
Author: Your Name
Author-email: your.email@example.com
Requires-Python: >=3.8,<4.0
Classifier: License :: Other/Proprietary License
Classifier: Programming Language :: Python :: 3
Classifier: Programming Language :: Python :: 3.8
Classifier: Programming Language :: Python :: 3.9
Classifier: Programming Language :: Python :: 3.10
Classifier: Programming Language :: Python :: 3.11
Classifier: Programming Language :: Python :: 3.12
Classifier: Programming Language :: Python :: 3.13
Requires-Dist: faiss-cpu (>=1.7.4,<2.0.0) ; sys_platform == "linux"
Requires-Dist: fastapi (>=0.95.0,<0.96.0)
Requires-Dist: httpx (>=0.23.3,<0.24.0)
Requires-Dist: langdetect (>=1.0.9,<2.0.0)
Requires-Dist: passlib[bcrypt] (>=1.7.4,<2.0.0)
Requires-Dist: pydantic (>=1.10.7,<2.0.0)
Requires-Dist: python-dateutil (>=2.8.2,<3.0.0)
Requires-Dist: python-jose[cryptography] (>=3.3.0,<4.0.0)
Requires-Dist: python-multipart (>=0.0.6,<0.0.7)
Requires-Dist: pyyaml (>=6.0,<7.0)
Requires-Dist: redis (>=4.5.5,<5.0.0)
Requires-Dist: sentence-transformers (>=2.2.2,<3.0.0)
Requires-Dist: spacy (>=3.5.0,<4.0.0)
Requires-Dist: uvicorn[standard] (>=0.21.1,<0.22.0)
